concrete_hnumpy-0.0.10-py3.9-nspkg.pth
concrete/hnumpy/__init__.py
concrete/hnumpy/file.py
concrete_hnumpy-0.0.10.dist-info/LICENSE
concrete_hnumpy-0.0.10.dist-info/METADATA
concrete_hnumpy-0.0.10.dist-info/WHEEL
concrete_hnumpy-0.0.10.dist-info/namespace_packages.txt
concrete_hnumpy-0.0.10.dist-info/top_level.txt
concrete_hnumpy-0.0.10.dist-info/RECORD
